labbench_comm/__init__.py
labbench_comm/_version.py
labbench_comm/cli.py
labbench_comm/devices/__init__.py
labbench_comm/devices/cpar/__init__.py
labbench_comm/devices/cpar/codec.py
labbench_comm/devices/cpar/cpar_central.py
labbench_comm/devices/cpar/definitions.py
labbench_comm/devices/cpar/instruction_codec.py
labbench_comm/devices/cpar/stimulation_data.py
labbench_comm/devices/cpar/waveform.py
labbench_comm/devices/cpar/functions/__init__.py
labbench_comm/devices/cpar/functions/clear_waveform_programs.py
labbench_comm/devices/cpar/functions/set_operating_mode.py
labbench_comm/devices/cpar/functions/set_waveform_program.py
labbench_comm/devices/cpar/functions/start_stimulation.py
labbench_comm/devices/cpar/functions/stop_stimulation.py
labbench_comm/devices/cpar/messages/__init__.py
labbench_comm/devices/cpar/messages/event_message.py
labbench_comm/devices/cpar/messages/status_message.py
labbench_comm/protocols/__init__.py
labbench_comm/protocols/bus_central.py
labbench_comm/protocols/destuffer.py
labbench_comm/protocols/device.py
labbench_comm/protocols/device_function.py
labbench_comm/protocols/device_message.py
labbench_comm/protocols/error_codes.py
labbench_comm/protocols/exceptions.py
labbench_comm/protocols/frame.py
labbench_comm/protocols/function_dispatcher.py
labbench_comm/protocols/manufacturer.py
labbench_comm/protocols/message_dispatcher.py
labbench_comm/protocols/packet.py
labbench_comm/protocols/functions/__init__.py
labbench_comm/protocols/functions/device_identification.py
labbench_comm/protocols/functions/ping.py
labbench_comm/protocols/messages/__init__.py
labbench_comm/protocols/messages/printf_message.py
labbench_comm/serial/__init__.py
labbench_comm/serial/async_connection.py
labbench_comm/serial/async_serial_connection.py
labbench_comm/serial/base.py
labbench_comm/serial/connection.py
labbench_comm/utils/__init__.py
labbench_comm/utils/additive_checksum.py
labbench_comm/utils/crc8_ccitt.py
labbench_comm-0.1.2.dist-info/licenses/LICENSE
labbench_comm-0.1.2.dist-info/METADATA
labbench_comm-0.1.2.dist-info/WHEEL
labbench_comm-0.1.2.dist-info/entry_points.txt
labbench_comm-0.1.2.dist-info/top_level.txt
labbench_comm-0.1.2.dist-info/RECORD
