Metadata-Version: 2.4
Name: labbench_comm
Version: 0.1.2
Summary: Communication with LabBench devices
Author: Kristian Hennings
License: MIT License
Project-URL: Homepage, https://labbench.io/
Project-URL: Repository, https://github.com/LabBench-Society/LabBench.Python
Project-URL: Issues, https://github.com/LabBench-Society/LabBench.Python/issues
Classifier: Development Status :: 3 - Alpha
Classifier: Intended Audience :: Science/Research
Classifier: Topic :: Scientific/Engineering
Classifier: Topic :: System :: Hardware :: Hardware Drivers
Classifier: License :: OSI Approved :: MIT License
Classifier: Programming Language :: Python :: 3
Classifier: Programming Language :: Python :: 3.9
Classifier: Programming Language :: Python :: 3.10
Classifier: Programming Language :: Python :: 3.11
Classifier: Programming Language :: Python :: 3.12
Requires-Python: >=3.12
License-File: LICENSE
Requires-Dist: pyserial>=3.5
Requires-Dist: typing-extensions>=4.5
Provides-Extra: dev
Requires-Dist: pytest>=8.0; extra == "dev"
Requires-Dist: pytest-asyncio>=0.23; extra == "dev"
Requires-Dist: pytest-cov>=5.0; extra == "dev"
Dynamic: license-file
